forecastmanager/__init__.py
forecastmanager/admin.py
forecastmanager/apps.py
forecastmanager/blocks.py
forecastmanager/constants.py
forecastmanager/forecast_settings.py
forecastmanager/forms.py
forecastmanager/models.py
forecastmanager/serializers.py
forecastmanager/tests.py
forecastmanager/urls.py
forecastmanager/utils.py
forecastmanager/views.py
forecastmanager/wagtail_hooks.py
forecastmanager/widgets.py
forecastmanager/locale/am/LC_MESSAGES/django.mo
forecastmanager/locale/am/LC_MESSAGES/django.po
forecastmanager/locale/ar/LC_MESSAGES/django.mo
forecastmanager/locale/ar/LC_MESSAGES/django.po
forecastmanager/locale/en/LC_MESSAGES/django.mo
forecastmanager/locale/en/LC_MESSAGES/django.po
forecastmanager/locale/es/LC_MESSAGES/django.mo
forecastmanager/locale/es/LC_MESSAGES/django.po
forecastmanager/locale/fr/LC_MESSAGES/django.mo
forecastmanager/locale/fr/LC_MESSAGES/django.po
forecastmanager/locale/sw/LC_MESSAGES/django.mo
forecastmanager/locale/sw/LC_MESSAGES/django.po
forecastmanager/management/__init__.py
forecastmanager/management/commands/__init__.py
forecastmanager/management/commands/clear_old_forecasts.py
forecastmanager/management/commands/generate_forecast.py
forecastmanager/migrations/0001_initial.py
forecastmanager/migrations/0002_remove_forecast_max_temp_remove_forecast_min_temp_and_more.py
forecastmanager/migrations/0003_alter_forecast_unique_together.py
forecastmanager/migrations/0004_forecastdataparameters_parameter_type_and_more.py
forecastmanager/migrations/0005_alter_forecastdataparameters_parameter.py
forecastmanager/migrations/0006_alter_forecastsetting_enable_auto_forecast.py
forecastmanager/migrations/0007_remove_forecastsetting_temp_units_and_more.py
forecastmanager/migrations/0008_alter_forecastdataparameters_parameter_unit.py
forecastmanager/migrations/0009_alter_forecastdataparameters_parameter_unit.py
forecastmanager/migrations/0010_alter_forecastdataparameters_parameter_type_and_more.py
forecastmanager-0.5.6.dist-info/METADATA
forecastmanager-0.5.6.dist-info/WHEEL
forecastmanager-0.5.6.dist-info/top_level.txt
forecastmanager-0.5.6.dist-info/RECORD
