Metadata-Version: 2.4
Name: forecastmanager
Version: 0.5.6
Summary: Integration of Weather City Forecasts Manager in Wagtail Projects.
Home-page: https://github.com/wmo-raf/forecastmanager
Author: Grace Amondi, Erick Otenyo
Author-email: miswa.grace@gmail.com, otenyo.erick@gmail.com
License: MIT
Classifier: Development Status :: 4 - Beta
Classifier: Environment :: Web Environment
Classifier: Intended Audience :: Developers
Classifier: License :: OSI Approved :: MIT License
Classifier: Operating System :: OS Independent
Classifier: Programming Language :: Python :: 3 :: Only
Classifier: Programming Language :: Python :: 3.9
Classifier: Programming Language :: Python :: Implementation :: CPython
Classifier: Topic :: Software Development :: Libraries :: Application Frameworks
Classifier: Topic :: Software Development :: Libraries :: Python Modules
Requires-Python: >=3.8
Requires-Dist: wagtail>=6.0
Requires-Dist: wagtailgeowidget>=8.2.1
Requires-Dist: django-filter
Requires-Dist: wagtail-icon-chooser>=0.3.1
Requires-Dist: wagtail-font-awesome-svg>=1.0.1
Requires-Dist: django-extensions
